gromacs_mdkit/__init__.py
gromacs_mdkit/cli.py
gromacs_mdkit/gromacs.py
gromacs_mdkit-1.0.4.dist-info/licenses/LICENSE
gromacs_mdkit-1.0.4.dist-info/METADATA
gromacs_mdkit-1.0.4.dist-info/WHEEL
gromacs_mdkit-1.0.4.dist-info/entry_points.txt
gromacs_mdkit-1.0.4.dist-info/top_level.txt
gromacs_mdkit-1.0.4.dist-info/RECORD
