Metadata-Version: 2.4
Name: gromacs-mdkit
Version: 1.0.4
Summary: A molecular dynamics preprocessing toolkit for GROMACS
Author-email: Pengcheng Li <your-email@example.com>
License: MIT
Project-URL: Homepage, https://github.com/yourusername/gromacs-mdkit
Project-URL: Bug Tracker, https://github.com/yourusername/gromacs-mdkit/issues
Keywords: gromacs,molecular dynamics,chemistry,simulation
Classifier: Programming Language :: Python :: 3
Classifier: License :: OSI Approved :: MIT License
Classifier: Operating System :: OS Independent
Classifier: Topic :: Scientific/Engineering :: Chemistry
Classifier: Intended Audience :: Science/Research
Requires-Python: >=3.8
License-File: LICENSE
Requires-Dist: rich>=13.0.0
Requires-Dist: periodictable>=1.6.0
Provides-Extra: dev
Requires-Dist: pytest; extra == "dev"
Requires-Dist: black; extra == "dev"
Requires-Dist: flake8; extra == "dev"
Dynamic: license-file
